konjingjing-1.0.0.dist-info/METADATA
konjingjing-1.0.0.dist-info/WHEEL
konjingjing.pyi
konjingjing/__init__.py
konjingjing/__init__.pyi
konjingjing/konjingjing.abi3.so
konjingjing/py.typed
py.typed
konjingjing-1.0.0.dist-info/RECORD
