Metadata-Version: 2.4
Name: konjingjing
Version: 1.0.0
Classifier: Programming Language :: Rust
Classifier: Programming Language :: Python :: Implementation :: CPython
Summary: Thai Citizen ID validation library
Keywords: thai,validation,citizen-id,thailand
Author-email: Nutchanon Ninyawee <me@nutchanon.org>
License-Expression: ISC
Requires-Python: >=3.9
